Metadata-Version: 2.1
Name: onnawscfn
Version: 0.0.5
Summary: Convenience Python module for AWS CloudFormation
Home-page: https://onnawscfn.oznetnerd.com
Author: Will Robinson
Author-email: will@oznetnerd.com
License: UNKNOWN
Platform: UNKNOWN
